DISCLAIMER
LICENSE
MANIFEST.in
NOTICE
RELEASE_NOTES.md
setup.py
licenses/LICENSE-ammonite.txt
licenses/LICENSE-asm.txt
licenses/LICENSE-clapper.txt
licenses/LICENSE-jeromq.txt
licenses/LICENSE-jline.txt
licenses/LICENSE-jopt-simple.txt
licenses/LICENSE-scala-stm.txt
licenses/LICENSE-scala.txt
licenses/LICENSE-scalaz.txt
licenses/LICENSE-slf4j.txt
toree/DISCLAIMER
toree/RELEASE_NOTES.md
toree/VERSION
toree/__init__.py
toree/__main__.py
toree/_version.py
toree/logo-64x64.png
toree/toreeapp.py
toree.egg-info/PKG-INFO
toree.egg-info/SOURCES.txt
toree.egg-info/dependency_links.txt
toree.egg-info/entry_points.txt
toree.egg-info/requires.txt
toree.egg-info/top_level.txt
toree/bin/run.sh
toree/lib/toree-assembly-0.5.0-incubating.jar